orion_finance_sdk/__init__.py
orion_finance_sdk/__main__.py
orion_finance_sdk/cli.py
orion_finance_sdk/contracts.py
orion_finance_sdk/encrypt.py
orion_finance_sdk/types.py
orion_finance_sdk/utils.py
orion_finance_sdk/abis/EncryptedVaultFactory.json
orion_finance_sdk/abis/OrionConfig.json
orion_finance_sdk/abis/OrionEncryptedVault.json
orion_finance_sdk/abis/OrionTransparentVault.json
orion_finance_sdk/abis/TransparentVaultFactory.json
orion_finance_sdk/js_sdk/bundle.js
orion_finance_sdk/js_sdk/kms_lib_bg.wasm
orion_finance_sdk/js_sdk/tfhe_bg.wasm
orion_finance_sdk-0.4.3.dist-info/licenses/LICENSE
orion_finance_sdk-0.4.3.dist-info/METADATA
orion_finance_sdk-0.4.3.dist-info/WHEEL
orion_finance_sdk-0.4.3.dist-info/entry_points.txt
orion_finance_sdk-0.4.3.dist-info/top_level.txt
orion_finance_sdk-0.4.3.dist-info/RECORD
