Metadata-Version: 2.4
Name: orion-finance-sdk
Version: 0.4.3
Summary: A Python SDK for interacting with Orion Finance smart contracts
Author: Orion Finance
Requires-Python: >=3.11
License-File: LICENSE
Requires-Dist: python-dotenv<2.0.0,>=1.1.0
Requires-Dist: numpy<3.0.0,>=2.2.0
Requires-Dist: typer<1.0.0,>=0.16.0
Requires-Dist: web3<8.0.0,>=7.12.0
Provides-Extra: dev
Requires-Dist: pre-commit<4.2.0,>=4.1.0; extra == "dev"
Requires-Dist: ruff<1.0.0,>=0.9.10; extra == "dev"
Requires-Dist: pydocstyle<6.4.0,>=6.3.0; extra == "dev"
Requires-Dist: pytest<8.4.0,>=8.3.5; extra == "dev"
Requires-Dist: pydeps<4.0.0,>=3.0.0; extra == "dev"
Dynamic: license-file
